{"changes": [{"formId": "covquymld0fcr3p7m", "recordId": "clk2mw8c00058honvpmda66zd", "parentRecordId": "clehh5dgn00593wmncwetimxu", "fields": {"mes": "2023-06", "colltmgkykvhxgij6": "ckvhq4hlcza9pfu4v", "rmrp": "Si", "poblacion_meta2": "Refugiados/as y migrantes", "PRVBG3_01_RM_NA": 140, "PRVBG3_01_RM_NN": 174, "PRVBG3_01_RM_MM": 254, "PRVBG3_01_RM_HH": 668, "PRVBG3_01_RM_OTR": 0, "PRVBG3_01_RM_LGBT": 11, "PRVBG3_01_RM_DS": 4, "PRVBG3_01_CUAL": "Los beb\u00e9s que ingresaron a los servicios junto con sus tutores recibieron kits beb\u00e9s y los tutores recibieron informaci\u00f3n."}}]}