{"changes": [{"formId": "ckq6yrylct8vun42s3r", "recordId": "clk2mn6sv000nhonvjhbognyz", "parentRecordId": "clk1lz6za0000y4nv55iug2og", "fields": {"mes": "2023-06", "colltmgkykvhxgij6": "csnyl4dlcza9pfr3g", "rmrp": "Si", "sector": "Comunicaci\u00f3n", "CO1_01": 1, "CO1_01_CUAL": "1 material de comunicaci\u00f3n y visibilidad tales como artes preparados por el \u00e1rea de comunicaci\u00f3n  (*backing, *post en redes sociales, *banners, * roll up)"}}, {"formId": "ckq6yrylct8vun42s3r", "recordId": "clk2mn76e000ohonvrfwnck6o", "parentRecordId": "clehh5dgf00003wmnh25jhvn2", "fields": {"mes": "2023-06", "colltmgkykvhxgij6": "csnyl4dlcza9pfr3g", "rmrp": "Si", "sector": "Comunicaci\u00f3n", "CO1_01": 1, "CO1_01_CUAL": "Para el cumplimiento del indicador, se realizaron las siguientes actividades:\n1. El 22 de junio se llev\u00f3 a cabo en el hotel Sheraton el evento +Pymes para el mundo, edici\u00f3n Compra con Prop\u00f3sito el cual const\u00f3 de 4 componentes: (i) en el componente de mercados, se realiz\u00f3 una rueda de negocios de alimentos y bebidas y dos micro ruedas, una de textiles y artesan\u00edas y otra de cuidado e hgiene personal; (ii) en el componente de innovaci\u00f3n, se realiz\u00f3 un panel con 3 ponentes; (iii) en el componente de financiamiento se realiz\u00f3 un foro con 4 ponentes y el componente de conocimiento se lo implent\u00f3 a tav\u00e9s de los dos anteriores. En este espacio se cont\u00f3 con la participaci\u00f3n de 20 empresas y 32 emprendedores."}}]}